abcmrt/ABC_MRT16.py
abcmrt/__init__.py
abcmrt/version.py
abcmrt/templates/ABC_MRT_FB_templates.mat
abcmrt16-1.0.2.dist-info/LICENSE.txt
abcmrt16-1.0.2.dist-info/METADATA
abcmrt16-1.0.2.dist-info/WHEEL
abcmrt16-1.0.2.dist-info/top_level.txt
abcmrt16-1.0.2.dist-info/RECORD
