Metadata-Version: 2.2
Name: abcmrt16
Version: 1.0.2
Summary: Package to run ABC-MRT16 intelligibility tests
Home-page: https://github.com/usnistgov/abcmrt16
Author: NTIA, PSCR
Author-email: PSCR@PSCR.gov
License: NIST software License
Classifier: Programming Language :: Python :: 3
Classifier: License :: Public Domain
Classifier: Operating System :: OS Independent
Requires-Python: >=3.6
License-File: LICENSE.txt
Requires-Dist: numpy
Requires-Dist: scipy
Requires-Dist: silero_vad
Dynamic: author
Dynamic: author-email
Dynamic: classifier
Dynamic: description
Dynamic: description-content-type
Dynamic: home-page
Dynamic: license
Dynamic: requires-dist
Dynamic: requires-python
Dynamic: summary
